coderev/__init__.py
coderev/api.py
coderev/compat.py
coderev/model.py
coderev/web_ui.py
coderev/htdocs/coderev.css
coderev/htdocs/coderev.js
coderev/upgrades/__init__.py
coderev/upgrades/db1.py
coderev/upgrades/db2.py
coderev/upgrades/db3.py
coderev/util/__init__.py
coderev/util/reviewer.py
TracCodeReviewer-1.0.0.dev0.dist-info/COPYING
TracCodeReviewer-1.0.0.dev0.dist-info/METADATA
TracCodeReviewer-1.0.0.dev0.dist-info/WHEEL
TracCodeReviewer-1.0.0.dev0.dist-info/entry_points.txt
TracCodeReviewer-1.0.0.dev0.dist-info/top_level.txt
TracCodeReviewer-1.0.0.dev0.dist-info/RECORD
